gradia/__init__.py
gradia/cli/__init__.py
gradia/cli/main.py
gradia/core/config.py
gradia/core/inspector.py
gradia/core/scenario.py
gradia/models/base.py
gradia/models/sklearn_wrappers.py
gradia/trainer/callbacks.py
gradia/trainer/engine.py
gradia/viz/server.py
gradia/viz/assets/logo.png
gradia/viz/static/css/style.css
gradia/viz/static/js/app.js
gradia/viz/templates/configure.html
gradia/viz/templates/index.html
gradia-1.0.0.dist-info/licenses/LICENSE
gradia-1.0.0.dist-info/METADATA
gradia-1.0.0.dist-info/WHEEL
gradia-1.0.0.dist-info/entry_points.txt
gradia-1.0.0.dist-info/top_level.txt
gradia-1.0.0.dist-info/RECORD
