Metadata-Version: 2.4
Name: gradia
Version: 1.0.0
Summary: Local-first ML training visualization and tracking dashboard.
Author-email: STiFLeR <stifler@example.com>
License: MIT License
Project-URL: Homepage, https://github.com/STiFLeR7/gradia
Project-URL: Bug Tracker, https://github.com/STiFLeR7/gradia/issues
Keywords: machine-learning,dashboard,visualization,tracking,mlops
Classifier: Programming Language :: Python :: 3
Classifier: License :: OSI Approved :: MIT License
Classifier: Operating System :: OS Independent
Classifier: Topic :: Scientific/Engineering :: Artificial Intelligence
Classifier: Topic :: System :: Monitoring
Requires-Python: >=3.9
License-File: LICENSE
Requires-Dist: scikit-learn
Requires-Dist: pandas
Requires-Dist: numpy
Requires-Dist: fastapi
Requires-Dist: uvicorn
Requires-Dist: typer
Requires-Dist: jinja2
Requires-Dist: watchdog
Requires-Dist: rich
Requires-Dist: psutil
Requires-Dist: tqdm
Dynamic: license-file
